FreeTrace/Localization.py
FreeTrace/PostProcessing.py
FreeTrace/Tracking.py
FreeTrace/__init__.py
FreeTrace/installation.py
FreeTrace/requirements.txt
FreeTrace/module/auxiliary.py
FreeTrace/module/cost_function.c
FreeTrace/module/data_load.py
FreeTrace/module/data_save.py
FreeTrace/module/deprecated.py
FreeTrace/module/gpu_module.py
FreeTrace/module/image_module.py
FreeTrace/module/image_pad.c
FreeTrace/module/load_models.py
FreeTrace/module/preprocessing.py
FreeTrace/module/regression.c
FreeTrace/module/trajectory_object.py
FreeTrace/module/xml_module.py
FreeTrace/module/cython_build/cost_function.pyx
FreeTrace/module/cython_build/cython_setup.py
FreeTrace/module/cython_build/image_pad.pyx
FreeTrace/module/cython_build/regression.pyx
freetrace-1.5.8.dist-info/METADATA
freetrace-1.5.8.dist-info/WHEEL
freetrace-1.5.8.dist-info/licenses/LICENSE
freetrace-1.5.8.dist-info/RECORD
