Metadata-Version: 2.4
Name: FreeTrace
Version: 1.5.8
Summary: FreeTrace
Project-URL: Homepage, https://github.com/JunwooParkSaribu/FreeTrace
Project-URL: Repository, https://doi.org/10.5281/zenodo.13336251
Author-email: Junwoo PARK <junwoo.park@sorbonne-universite.fr>
Maintainer-email: Junwoo PARK <junwoo.park@sorbonne-universite.fr>
License:                     GNU GENERAL PUBLIC LICENSE
License-File: LICENSE
Keywords: SPT
Classifier: License :: OSI Approved :: GNU General Public License v3 or later (GPLv3+)
Classifier: Operating System :: POSIX :: Linux
Classifier: Programming Language :: Python :: 3
Requires-Python: >=3.10
Provides-Extra: cli
Requires-Dist: click; extra == 'cli'
Requires-Dist: rich; extra == 'cli'
Provides-Extra: gui
Requires-Dist: pyqt6; extra == 'gui'
